magbox/__init__.py
magbox/boxlib.py
magbox/heff.py
magbox/llg.py
magbox/spin.py
magbox-0.1.4.dist-info/METADATA
magbox-0.1.4.dist-info/WHEEL
magbox-0.1.4.dist-info/RECORD
