Metadata-Version: 2.4
Name: magbox
Version: 0.1.4
Summary: Solve lattice llg numerically
Requires-Python: >=3.9
Requires-Dist: numpy>=2.0.2
Requires-Dist: torch==2.8.0
Requires-Dist: tqdm>=4.67.1
